phase0/README.md
phase0/__init__.py
phase0/action.py
phase0/actions.py
phase0/phase0.py
phase0/repetition.py
phase0/trace.py
phase0/phase0/PHASE0_FREEZE.md
phase0/phase0/docs/PHASE0_FINAL_VERIFICATION.md
phase0/phase0/docs/README.md
phase1/README.md
phase1/__init__.py
phase1/boundary.py
phase1/cluster.py
phase1/distance.py
phase1/pattern.py
phase1/phase1.py
phase1/docs/PHASE1_COMPLIANCE_VERIFICATION.md
phase1/docs/README.md
phase1/phase1/PHASE1_FREEZE.md
phase1/phase1/PHASE1_IMPLEMENTATION_PROMPT.md
phase1/phase1/PHASE1_IMPLEMENTATION_PROMPT_FINAL.md
phase1/phase1/PHASE1_TRANSITION.md
phase1/phase1/README.md
phase2/README.md
phase2/__init__.py
phase2/identity.py
phase2/persistence.py
phase2/phase2.py
phase2/repeatable.py
phase2/stability.py
phase2/docs/PHASE2_COMPLIANCE_VERIFICATION.md
phase2/docs/README.md
phase2/phase2/PHASE2_FREEZE.md
phase2/phase2/PHASE2_IMPLEMENTATION_PROMPT_FINAL.md
phase2/phase2/PHASE2_PROMPT_SUMMARY.md
phase2/phase2/README.md
phase3/__init__.py
phase3/dependency.py
phase3/graph.py
phase3/influence.py
phase3/interaction.py
phase3/persistence.py
phase3/phase3.py
phase3/relation.py
phase3/stability.py
phase3/phase3/PHASE3_COMPLETION_PROMPT.md
phase3/phase3/PHASE3_FREEZE.md
phase3/phase3/PHASE3_FREEZE_new.md
phase3/phase3/PHASE3_IMPLEMENTATION_FINAL.md
phase3/phase3/PHASE3_IMPLEMENTATION_PROMPT_FINAL.md
phase3/phase3/PHASE3_PERSISTENCE.md
phase3/phase3/PHASE3_PROMPT_SUMMARY.md
phase3/phase3/README.md
phase4/__init__.py
phase4/alias.py
phase4/phase4.py
phase4/phase4/PHASE4_FREEZE.md
phase4/phase4/PHASE4_IMPLEMENTATION_PLAN_FINAL.md
threshold_onset-1.0.0.dist-info/licenses/LICENSE
tools/README.md
tools/version_control.py
tools/watch_version.py
tools/docs/README.md
tools/docs/VERSION_CONTROL.md
threshold_onset-1.0.0.dist-info/METADATA
threshold_onset-1.0.0.dist-info/WHEEL
threshold_onset-1.0.0.dist-info/top_level.txt
threshold_onset-1.0.0.dist-info/RECORD
