Metadata-Version: 2.4
Name: threshold-onset
Version: 1.0.0
Summary: A foundational system exploring structure emergence through action, trace, and repetition
Home-page: https://github.com/chavalasantosh/THRESHOLDONSET
Author: ChavalaSantosh
Author-email: ChavalaSantosh <santoshysc@gmail.com>
Maintainer: ChavalaSantosh
Maintainer-email: santoshysc@gmail.com
License: MIT
Project-URL: Homepage, https://github.com/chavalasantosh/THRESHOLDONSET
Project-URL: Repository, https://github.com/chavalasantosh/THRESHOLDONSET.git
Project-URL: Issues, https://github.com/chavalasantosh/THRESHOLDONSET/issues
Keywords: structure,emergence,foundational,phases,action,knowledge
Classifier: Development Status :: 5 - Production/Stable
Classifier: Intended Audience :: Developers
Classifier: Intended Audience :: Science/Research
Classifier: Topic :: Scientific/Engineering
Classifier: Topic :: Software Development :: Libraries :: Python Modules
Classifier: License :: OSI Approved :: MIT License
Classifier: Programming Language :: Python :: 3
Classifier: Programming Language :: Python :: 3.8
Classifier: Programming Language :: Python :: 3.9
Classifier: Programming Language :: Python :: 3.10
Classifier: Programming Language :: Python :: 3.11
Classifier: Programming Language :: Python :: 3.12
Classifier: Operating System :: OS Independent
Requires-Python: >=3.8
License-File: LICENSE
Provides-Extra: dev
Requires-Dist: pylint>=3.0.0; extra == "dev"
Requires-Dist: watchfiles>=0.21.0; extra == "dev"
Provides-Extra: all
Requires-Dist: pylint>=3.0.0; extra == "all"
Requires-Dist: watchfiles>=0.21.0; extra == "all"
Requires-Dist: numpy; extra == "all"
Dynamic: author
Dynamic: home-page
Dynamic: license-file
Dynamic: maintainer
Dynamic: maintainer-email
Dynamic: requires-python
